novadax/__init__.py
novadax/request_client.py
novadax/websocket_client.py
novadax/exception/__init__.py
novadax/exception/novadax_exception.py
novadax/kernel/__init__.py
novadax/kernel/encryptor.py
novadax/kernel/http/__init__.py
novadax/kernel/http/base_http_auth.py
novadax/kernel/http/base_http_client.py
novadax/kernel/websocket/__init__.py
novadax/kernel/websocket/websocket_client.py
novadax-1.1.3.dist-info/METADATA
novadax-1.1.3.dist-info/WHEEL
novadax-1.1.3.dist-info/top_level.txt
novadax-1.1.3.dist-info/RECORD
