Metadata-Version: 2.1
Name: novadax
Version: 1.1.3
Summary: NovaDAX API SDK
Home-page: https://doc.novadax.com/
Author: NovaDAX
Author-email: support@novadax.com
License: UNKNOWN
Platform: UNKNOWN
Requires-Dist: requests (<3,>=2)
Requires-Dist: python-socketio[client]
